{
  "pins": {
    "nixos-hardware": {
      "type": "Git",
      "repository": {
        "type": "GitHub",
        "owner": "nixos",
        "repo": "nixos-hardware"
      },
      "branch": "master",
      "revision": "e8516a23524cc9083f5a02a8d64d14770e4c7c09",
      "url": "https://github.com/nixos/nixos-hardware/archive/e8516a23524cc9083f5a02a8d64d14770e4c7c09.tar.gz",
      "hash": "135w93vkcrvdv4rp34qi8682sgjqzp6k89k5wm2kf8f7dsqmx36k"
    },
    "nixos-unstable": {
      "type": "Channel",
      "name": "nixos-unstable",
      "url": "https://releases.nixos.org/nixos/unstable/nixos-25.05beta724962.d70bd19e0a38/nixexprs.tar.xz",
      "hash": "0f38k2h41xib1z6idb36bvysligq200hrqbbdxaxak9vdibzgmj7"
    },
    "nur-expressions": {
      "type": "Git",
      "repository": {
        "type": "GitLab",
        "repo_path": "rycee/nur-expressions",
        "server": "https://gitlab.com/"
      },
      "branch": "master",
      "revision": "5a5aea6627a4c360ba030ddadeda63d1ad294125",
      "url": "https://gitlab.com/api/v4/projects/rycee%2Fnur-expressions/repository/archive.tar.gz?sha=5a5aea6627a4c360ba030ddadeda63d1ad294125",
      "hash": "03iyi9w0rddrg5pb8m5vxdqhwy03jcqrkr3ylxqkjvymnfxjlrig"
    },
    "vim-afterimage": {
      "type": "GitRelease",
      "repository": {
        "type": "GitHub",
        "owner": "tpope",
        "repo": "vim-afterimage"
      },
      "pre_releases": false,
      "version_upper_bound": null,
      "release_prefix": null,
      "version": "v2.2",
      "revision": "782352096f95dcab574fec93e787d0b2e18b362e",
      "url": "https://api.github.com/repos/tpope/vim-afterimage/tarball/v2.2",
      "hash": "0r56yp73sp69ay932rd0jzimj0al1ixqqpqw3l16d4m326zd0zbv"
    }
  },
  "version": 3
}